foo/__init__.py
foo/hello.py
package_foo-0.0.1.dist-info/METADATA
package_foo-0.0.1.dist-info/WHEEL
package_foo-0.0.1.dist-info/entry_points.txt
package_foo-0.0.1.dist-info/top_level.txt
package_foo-0.0.1.dist-info/RECORD
