Metadata-Version: 2.1
Name: package-foo
Version: 0.0.1
Summary: foo is a demo project
Author-email: python_app_tech <python_app_tech@126.com>
Classifier: Programming Language :: Python :: 3
Classifier: License :: OSI Approved :: MIT License
Classifier: Operating System :: OS Independent
Requires-Python: >=3.8
